easy_ml_preprocess/__init__.py
easy_ml_preprocess/custom_exception.py
easy_ml_preprocess/logger.py
easy_ml_preprocess/remove_outliers.py
easymlpreprocess1-0.0.4.dist-info/LICENSE
easymlpreprocess1-0.0.4.dist-info/METADATA
easymlpreprocess1-0.0.4.dist-info/WHEEL
easymlpreprocess1-0.0.4.dist-info/top_level.txt
easymlpreprocess1-0.0.4.dist-info/RECORD
